Workbook
Name Slicer_Region: #N/A
Name Slicer_Payment_Method: #N/A
Name Slicer_Customer_Name: #N/A

Sheet Project Instructions
A1: PR. Final Project - "Data Intelligence Dashboard"
A2: Dataset: Use the 'Final Project Dataset' sheet containing 200+ records of customer transactions. Objective: Create a full-fledged analysis and reporting solution using Excel to analyze customer transactions, find insights, and build visualizations and dashboards. Key Topics to Implement: - Date & Time Functions: TODAY, NOW, DATEDIF, EOMONTH - FILTER Function for multi-value returns - Conditional Formatting with Icons/Arrows - Create Timestamp (using NOW and iterative calculations) - WHAT-IF Analysis: Scenario Manager, Goal Seek - Linear Regression using Data Analysis Toolpak - Data Analysis & Storytelling from the dataset - Use GroupBy concepts to find High-Value Customers using formulas - Create Dashboard using: - Pivot Tables - Pivot Charts (Bar, Line, Pie) - Slicers and Timelines - KPI Indicators with Conditional Formatting - Find most frequently purchased product or repeating names using formulas - Compare two lists and extract matching names in a new column - Create Abbreviations using TEXT functions - Build a final report with insights and storytelling Deliverable: - Well-structured workbook with multiple sheets (Raw Data, Analysis, Visualizations, Dashboard) - Summary Insights with key metrics: Total Revenue, Top Customers, Most Sold Products, Regional Sales - Use of all required formulas and functions as listed above

Sheet Sales By Month
A3: Year-Month | B3: Sum of Total_Amount
A4: 2024-04 | B4: 6579.79
A5: 2024-05 | B5: 5769.78
A6: 2024-06 | B6: 1379.84
A7: 2024-07 | B7: 4649.77
A8: 2024-08 | B8: 3869.8
A9: 2024-09 | B9: 999.91
A10: 2024-10 | B10: 9599.84
A11: 2024-11 | B11: 1499.9
A12: 2024-12 | B12: 6799.72
A13: 2025-01 | B13: 3299.92
A14: 2025-02 | B14: 7279.74
A15: 2025-03 | B15: 2999.81
... A17: Grand Total | B17: 57427.79

Sheet Sales By Product
A3: Product_Name | B3: Sum of Total_Amount
A4: Blender | B4: 2039.66
A5: Bookshelf | B5: 4799.68
A6: Coffee Maker | B6: 1199.85
A7: Desk | B7: 8099.73
A8: Headphones | B8: 2249.85
A9: Keyboard | B9: 1439.84
A10: Laptop | B10: 8099.91
A11: Monitor | B11: 4499.82
A12: Office Chair | B12: 5399.73
A13: Smartphone | B13: 19599.72
A14: Grand Total | B14: 57427.79

Sheet Customer Count
A3: Region | B3: Count of Customer_Name
A4: Central | B4: 54
A5: East | B5: 48
A6: North | B6: 59
A7: South | B7: 42
A8: West | B8: 47
A9: Grand Total | B9: 250

Sheet kpi helper
A3: Distinct Count of Customer_ID | B3: Distinct Count of Transaction_ID | C3: Sum of Total_Amount
A4: 1 | B4: 3 | C4: 1749.92

Sheet Product count per category
A3: Product_Name | B3: Sum of Quantity
A4: Bookshelf | B4: 3
A5: Headphones | B5: 4
A6: Smartphone | B6: 1
A7: Grand Total | B7: 8

Sheet Raw Data
A1: Transaction_ID | B1: Date | C1: Customer_ID | D1: Customer_Name | E1: Product_ID | F1: Product_Name | G1: Category | H1: Quantity | I1: Unit_Price | J1: Payment_Method | K1: Region | L1: Customer_Segment | M1: Customer_Since | N1: Total_Amount | O1: Year-Month | P1: Month | Q1: Year
A2: TRX0155 | B2: 45393 | C2: CUST023 | D2: Paul Baker | E2: P009 | F2: Monitor | G2: Electronics | H2: 3 | I2: 249.99 | J2: Cash | K2: Central | L2: Basic | M2: 44425 | N2: 749.97 | O2: =TEXT(B2,"yyyy-mm") -> 2024-04 | P2: =MONTH(B2) -> 4 | Q2: =YEAR(B2) -> 2024
A3: TRX0023 | B3: 45396 | C3: CUST013 | D3: Joseph Jackson | E3: P009 | F3: Monitor | G3: Electronics | H3: 3 | I3: 249.99 | J3: Credit Card | K3: Central | L3: Premium | M3: 44575 | N3: 749.97 | O3: =TEXT(B3,"yyyy-mm") -> 2024-04 | P3: =MONTH(B3) -> 4 | Q3: =YEAR(B3) -> 2024
A4: TRX0139 | B4: 45399 | C4: CUST021 | D4: Kevin Scott | E4: P005 | F4: Blender | G4: Appliances | H4: 3 | I4: 59.99 | J4: PayPal | K4: South | L4: Standard | M4: 45262 | N4: 179.97 | O4: =TEXT(B4,"yyyy-mm") -> 2024-04 | P4: =MONTH(B4) -> 4 | Q4: =YEAR(B4) -> 2024
A5: TRX0043 | B5: 45400 | C5: CUST046 | D5: Kathleen Bennett | E5: P005 | F5: Blender | G5: Appliances | H5: 3 | I5: 59.99 | J5: Cash | K5: North | L5: Premium | M5: 45114 | N5: 179.97 | O5: =TEXT(B5,"yyyy-mm") -> 2024-04 | P5: =MONTH(B5) -> 4 | Q5: =YEAR(B5) -> 2024
A6: TRX0212 | B6: 45400 | C6: CUST003 | D6: Michael Brown | E6: P008 | F6: Bookshelf | G6: Furniture | H6: 5 | I6: 149.99 | J6: Credit Card | K6: North | L6: Premium | M6: 45295 | N6: 749.95 | O6: =TEXT(B6,"yyyy-mm") -> 2024-04 | P6: =MONTH(B6) -> 4 | Q6: =YEAR(B6) -> 2024
A7: TRX0092 | B7: 45403 | C7: CUST024 | D7: Dorothy Nelson | E7: P005 | F7: Blender | G7: Appliances | H7: 2 | I7: 59.99 | J7: Cash | K7: West | L7: Standard | M7: 44746 | N7: 119.98 | O7: =TEXT(B7,"yyyy-mm") -> 2024-04 | P7: =MONTH(B7) -> 4 | Q7: =YEAR(B7) -> 2024
A8: TRX0193 | B8: 45403 | C8: CUST024 | D8: Dorothy Nelson | E8: P003 | F8: Headphones | G8: Electronics | H8: 5 | I8: 149.99 | J8: Credit Card | K8: Central | L8: Standard | M8: 44418 | N8: 749.95 | O8: =TEXT(B8,"yyyy-mm") -> 2024-04 | P8: =MONTH(B8) -> 4 | Q8: =YEAR(B8) -> 2024
A9: TRX0240 | B9: 45403 | C9: CUST017 | D9: Charles Allen | E9: P005 | F9: Blender | G9: Appliances | H9: 3 | I9: 59.99 | J9: Debit Card | K9: South | L9: Basic | M9: 45007 | N9: 179.97 | O9: =TEXT(B9,"yyyy-mm") -> 2024-04 | P9: =MONTH(B9) -> 4 | Q9: =YEAR(B9) -> 2024
A10: TRX0135 | B10: 45405 | C10: CUST009 | D10: Robert Thomas | E10: P001 | F10: Laptop | G10: Electronics | H10: 3 | I10: 899.99 | J10: PayPal | K10: East | L10: Standard | M10: 45299 | N10: 2699.97 | O10: =TEXT(B10,"yyyy-mm") -> 2024-04 | P10: =MONTH(B10) -> 4 | Q10: =YEAR(B10) -> 2024
A11: TRX0185 | B11: 45408 | C11: CUST026 | D11: Karen Hill | E11: P005 | F11: Blender | G11: Appliances | H11: 3 | I11: 59.99 | J11: Cash | K11: West | L11: Premium | M11: 45207 | N11: 179.97 | O11: =TEXT(B11,"yyyy-mm") -> 2024-04 | P11: =MONTH(B11) -> 4 | Q11: =YEAR(B11) -> 2024
A12: TRX0138 | B12: 45408 | C12: CUST022 | D12: Susan Green | E12: P008 | F12: Bookshelf | G12: Furniture | H12: 1 | I12: 149.99 | J12: Credit Card | K12: West | L12: Standard | M12: 45103 | N12: 149.99 | O12: =TEXT(B12,"yyyy-mm") -> 2024-04 | P12: =MONTH(B12) -> 4 | Q12: =YEAR(B12) -> 2024
A13: TRX0209 | B13: 45408 | C13: CUST046 | D13: Kathleen Bennett | E13: P008 | F13: Bookshelf | G13: Furniture | H13: 5 | I13: 149.99 | J13: Debit Card | K13: North | L13: Basic | M13: 44830 | N13: 749.95 | O13: =TEXT(B13,"yyyy-mm") -> 2024-04 | P13: =MONTH(B13) -> 4 | Q13: =YEAR(B13) -> 2024
... A251: TRX0064 | B251: 45758 | C251: CUST031 | D251: Steven Turner | E251: P010 | F251: Keyboard | G251: Electronics | H251: 3 | I251: 89.99 | J251: Debit Card | K251: North | L251: Premium | M251: 44878 | N251: 269.97 | O251: =TEXT(B251,"yyyy-mm") -> 2025-04 | P251: =MONTH(B251) -> 4 | Q251: =YEAR(B251) -> 2025

Sheet Top 5 Customer
A3: Customer Name | B3: Sum of Total Amount
A4: Paul Baker | B4: 8309.74
A5: Patricia Moore | B5: 9799.73
A6: Mark Carter | B6: 15659.65
A7: Edward Mitchell | B7: 11919.77
A8: Barbara Young | B8: 10649.8
A9: Grand Total | B9: 56338.69

Sheet Analysis
A1: Metric | B1: Value | E1: Product | F1: Total Amount | G1: Quentity | I1: Year-Month | J1: Total Amount | K1: Last Month Revenue | L1: Growth Rate
A2: Total Transaction | B2: =COUNTA('Raw Data'!C2:C251) -> 250 | E2: {=_xlfn.UNIQUE('Raw Data'!F2:F251)} -> Monitor | F2: =SUMIFS('Raw Data'!N2:N251,'Raw Data'!F2:F251,E2) -> 21999.12 | G2: =SUMIFS('Raw Data'!H2:H251,'Raw Data'!F2:F251,E2) -> 88 | I2: {=_xlfn.UNIQUE('Raw Data'!O2:O251)} -> 2024-04 | J2: =SUMIFS('Raw Data'!N2:N251,'Raw Data'!O2:O251,I2) -> 20919.33 | L2: =IFERROR((K2-J2)/K2,"")
A3: Total Customers | B3: {=COUNTA(_xlfn.UNIQUE('Raw Data'!D2:D251))} -> 50 | E3: Blender | F3: =SUMIFS('Raw Data'!N3:N252,'Raw Data'!F3:F252,E3) -> 5219.13 | G3: =SUMIFS('Raw Data'!H3:H252,'Raw Data'!F3:F252,E3) -> 87 | I3: 2024-05 | J3: =SUMIFS('Raw Data'!N3:N252,'Raw Data'!O3:O252,I3) -> 17039.35 | K3: =SUMIFS('Raw Data'!N2:N251,'Raw Data'!O2:O251,I2) -> 20919.33 | L3: =IFERROR((J3-K3)/K3,"") -> -0.18547344
A4: Total Revenue | B4: =SUM('Raw Data'!N2:N251) -> 229192.47 | E4: Bookshelf | F4: =SUMIFS('Raw Data'!N4:N253,'Raw Data'!F4:F253,E4) -> 15298.98 | G4: =SUMIFS('Raw Data'!H4:H253,'Raw Data'!F4:F253,E4) -> 102 | I4: 2024-06 | J4: =SUMIFS('Raw Data'!N4:N253,'Raw Data'!O4:O253,I4) -> 19299.45 | K4: =SUMIFS('Raw Data'!N3:N252,'Raw Data'!O3:O252,I3) -> 17039.35 | L4: =IFERROR((J4-K4)/K4,"") -> 0.13264004
A5: Avarage Order Value | B5: =AVERAGE('Raw Data'!N2:N251) -> 916.76988 | E5: Headphones | F5: =SUMIFS('Raw Data'!N5:N254,'Raw Data'!F5:F254,E5) -> 7049.53 | G5: =SUMIFS('Raw Data'!H5:H254,'Raw Data'!F5:F254,E5) -> 47 | I5: 2024-07 | J5: =SUMIFS('Raw Data'!N5:N254,'Raw Data'!O5:O254,I5) -> 18479.4 | K5: =SUMIFS('Raw Data'!N4:N253,'Raw Data'!O4:O253,I4) -> 19299.45 | L5: =IFERROR((J5-K5)/K5,"") -> -0.042490848
A6: Top Product | B6: {=INDEX(E1:E11,MATCH(MAX(F1:F11),F1:F11,0))} -> Laptop | C6: =MAX(F1:F11) -> 67499.25 | E6: Laptop | F6: =SUMIFS('Raw Data'!N6:N255,'Raw Data'!F6:F255,E6) -> 67499.25 | G6: =SUMIFS('Raw Data'!H6:H255,'Raw Data'!F6:F255,E6) -> 75 | I6: 2024-08 | J6: =SUMIFS('Raw Data'!N6:N255,'Raw Data'!O6:O255,I6) -> 15759.43 | K6: =SUMIFS('Raw Data'!N5:N254,'Raw Data'!O5:O254,I5) -> 18479.4 | L6: =IFERROR((J6-K6)/K6,"") -> -0.1471893
A7: Region WIth Highest Sales | B7: {=INDEX(E13:E18,MATCH(MAX(F13:F18),F13:F18,0))} -> East | C7: =MAX(F13:F18) -> 59288.39 | E7: Smartphone | F7: =SUMIFS('Raw Data'!N7:N256,'Raw Data'!F7:F256,E7) -> 67199.04 | G7: =SUMIFS('Raw Data'!H7:H256,'Raw Data'!F7:F256,E7) -> 96 | I7: 2024-09 | J7: =SUMIFS('Raw Data'!N7:N256,'Raw Data'!O7:O256,I7) -> 12989.51 | K7: =SUMIFS('Raw Data'!N6:N255,'Raw Data'!O6:O255,I6) -> 15759.43 | L7: =IFERROR((J7-K7)/K7,"") -> -0.1757627
A8: Top Salesperson | B8: {=INDEX(A11:A61,MATCH(MAX(B11:B61),B11:B61,0))} -> Mark Carter | C8: =MAX(B11:B61) -> 15659.65 | E8: Desk | F8: =SUMIFS('Raw Data'!N8:N257,'Raw Data'!F8:F257,E8) -> 23399.22 | G8: =SUMIFS('Raw Data'!H8:H257,'Raw Data'!F8:F257,E8) -> 78 | I8: 2024-10 | J8: =SUMIFS('Raw Data'!N8:N257,'Raw Data'!O8:O257,I8) -> 20609.52 | K8: =SUMIFS('Raw Data'!N7:N256,'Raw Data'!O7:O256,I7) -> 12989.51 | L8: =IFERROR((J8-K8)/K8,"") -> 0.58662798
E9: Coffee Maker | F9: =SUMIFS('Raw Data'!N9:N258,'Raw Data'!F9:F258,E9) -> 3119.61 | G9: =SUMIFS('Raw Data'!H9:H258,'Raw Data'!F9:F258,E9) -> 39 | I9: 2024-11 | J9: =SUMIFS('Raw Data'!N9:N258,'Raw Data'!O9:O258,I9) -> 12309.44 | K9: =SUMIFS('Raw Data'!N8:N257,'Raw Data'!O8:O257,I8) -> 20609.52 | L9: =IFERROR((J9-K9)/K9,"") -> -0.40273039
E10: Keyboard | F10: =SUMIFS('Raw Data'!N10:N259,'Raw Data'!F10:F259,E10) -> 8009.11 | G10: =SUMIFS('Raw Data'!H10:H259,'Raw Data'!F10:F259,E10) -> 89 | I10: 2024-12 | J10: =SUMIFS('Raw Data'!N10:N259,'Raw Data'!O10:O259,I10) -> 23039.3 | K10: =SUMIFS('Raw Data'!N9:N258,'Raw Data'!O9:O258,I9) -> 12309.44 | L10: =IFERROR((J10-K10)/K10,"") -> 0.87167735
A11: Customer Name | B11: Total Amount | E11: Office Chair | F11: =SUMIFS('Raw Data'!N11:N260,'Raw Data'!F11:F260,E11) -> 10399.48 | G11: =SUMIFS('Raw Data'!H11:H260,'Raw Data'!F11:F260,E11) -> 52 | I11: 2025-01 | J11: =SUMIFS('Raw Data'!N11:N260,'Raw Data'!O11:O260,I11) -> 25799.15 | K11: =SUMIFS('Raw Data'!N10:N259,'Raw Data'!O10:O259,I10) -> 23039.3 | L11: =IFERROR((J11-K11)/K11,"") -> 0.1197888
A12: {=_xlfn.UNIQUE('Raw Data'!D2:D251)} -> Paul Baker | B12: =SUMIFS('Raw Data'!N2:N251,'Raw Data'!D2:D251,A12) -> 8309.74 | I12: 2025-02 | J12: =SUMIFS('Raw Data'!N12:N261,'Raw Data'!O12:O261,I12) -> 16069.38 | K12: =SUMIFS('Raw Data'!N11:N260,'Raw Data'!O11:O260,I11) -> 25799.15 | L12: =IFERROR((J12-K12)/K12,"") -> -0.37713529
A13: Joseph Jackson | B13: =SUMIFS('Raw Data'!N3:N252,'Raw Data'!D3:D252,A13) -> 6949.84 | E13: Region | F13: Total Amount | I13: 2025-03 | J13: =SUMIFS('Raw Data'!N13:N262,'Raw Data'!O13:O262,I13) -> 19899.38 | K13: =SUMIFS('Raw Data'!N12:N261,'Raw Data'!O12:O261,I12) -> 16069.38 | L13: =IFERROR((J13-K13)/K13,"") -> 0.23834149
A14: Kevin Scott | B14: =SUMIFS('Raw Data'!N4:N253,'Raw Data'!D4:D253,A14) -> 3259.87 | E14: {=_xlfn.UNIQUE('Raw Data'!K2:K251)} -> Central | F14: =SUMIFS('Raw Data'!N2:N251,'Raw Data'!K2:K251,E14) -> 41288.34 | I14: 2025-04 | J14: =SUMIFS('Raw Data'!N14:N263,'Raw Data'!O14:O263,I14) -> 6979.83 | K14: =SUMIFS('Raw Data'!N13:N262,'Raw Data'!O13:O262,I13) -> 19899.38 | L14: =IFERROR((J14-K14)/K14,"") -> -0.64924385
A15: Kathleen Bennett | B15: =SUMIFS('Raw Data'!N5:N254,'Raw Data'!D5:D254,A15) -> 4309.81 | E15: South | F15: =SUMIFS('Raw Data'!N3:N252,'Raw Data'!K3:K252,E15) -> 36398.75
A16: Michael Brown | B16: =SUMIFS('Raw Data'!N6:N255,'Raw Data'!D6:D255,A16) -> 6169.74 | E16: North | F16: =SUMIFS('Raw Data'!N4:N253,'Raw Data'!K4:K253,E16) -> 50808.31
A17: Dorothy Nelson | B17: =SUMIFS('Raw Data'!N7:N256,'Raw Data'!D7:D256,A17) -> 8269.79 | E17: West | F17: =SUMIFS('Raw Data'!N5:N254,'Raw Data'!K5:K254,E17) -> 41408.68
A18: Charles Allen | B18: =SUMIFS('Raw Data'!N8:N257,'Raw Data'!D8:D257,A18) -> 5089.73 | E18: East | F18: =SUMIFS('Raw Data'!N6:N255,'Raw Data'!K6:K255,E18) -> 59288.39
A19: Robert Thomas | B19: =SUMIFS('Raw Data'!N9:N258,'Raw Data'!D9:D258,A19) -> 3509.9
A20: Karen Hill | B20: =SUMIFS('Raw Data'!N10:N259,'Raw Data'!D10:D259,A20) -> 8009.77
A21: Susan Green | B21: =SUMIFS('Raw Data'!N11:N260,'Raw Data'!D11:D260,A21) -> 1979.89
A22: Peter Richardson | B22: =SUMIFS('Raw Data'!N12:N261,'Raw Data'!D12:D261,A22) -> 5949.85
A23: Dennis Gray | B23: =SUMIFS('Raw Data'!N13:N262,'Raw Data'!D13:D262,A23) -> 479.92
A24: Michelle Rogers | B24: =SUMIFS('Raw Data'!N14:N263,'Raw Data'!D14:D263,A24) -> 4199.94
A25: George Adams | B25: =SUMIFS('Raw Data'!N15:N264,'Raw Data'!D15:D264,A25) -> 3779.93
A26: Mark Carter | B26: =SUMIFS('Raw Data'!N16:N265,'Raw Data'!D16:D265,A26) -> 15659.65
A27: Maria Garcia | B27: =SUMIFS('Raw Data'!N17:N266,'Raw Data'!D17:D266,A27) -> 1909.93
A28: Virginia Sanders | B28: =SUMIFS('Raw Data'!N18:N267,'Raw Data'!D18:D267,A28) -> 4789.79
A29: Barbara Young | B29: =SUMIFS('Raw Data'!N19:N268,'Raw Data'!D19:D268,A29) -> 10649.8
A30: Patricia Moore | B30: =SUMIFS('Raw Data'!N20:N269,'Raw Data'!D20:D269,A30) -> 9799.73
... A61: John Smith | B61: =SUMIFS('Raw Data'!N51:N300,'Raw Data'!D51:D300,A61) -> 599.96

Sheet Summary
A1: Summary
A3: Dashboard summary generated on:= | B3: =NOW() -> 45970.85
A5: Total Revenue: ₹229,192.47
A6: Total Transactions: 250
A7: Average Order Value: ₹916.77
A8: Total Unique Customers: 50
A9: Top Salesperson by Revenue: Mark Carter (₹15,659.65)
A10: Top Product by Revenue: Laptop (₹67,499.25)
A11: Top Region by Revenue: East
A12: Most Frequently Purchased Product: Bookshelf
A14: Top 5 Customers By Revenue
A16: Customer Name | B16: Total Amount
A17: {=INDEX(_xlfn.ANCHORARRAY(Analysis!$A$12),MATCH(LARGE(Analysis!$B$12:$B$61,1),Analysis!$B$12:$B$61,0))} -> Mark Carter | B17: =LARGE(Analysis!$B$12:$B$61,1) -> 15659.65
A18: {=INDEX(_xlfn.ANCHORARRAY(Analysis!A12),MATCH(LARGE(Analysis!B12:B61,2),Analysis!B12:B61,0))} -> Edward Mitchell | B18: 11919.77
A19: {=INDEX(_xlfn.ANCHORARRAY(Analysis!A12),MATCH(LARGE(Analysis!B12:B61,3),Analysis!B12:B61,0))} -> Barbara Young | B19: 10649.8
A20: {=INDEX(_xlfn.ANCHORARRAY(Analysis!A12),MATCH(LARGE(Analysis!B12:B61,4),Analysis!B12:B61,0))} -> Patricia Moore | B20: 9799.73
A21: {=INDEX(_xlfn.ANCHORARRAY(Analysis!A12),MATCH(LARGE(Analysis!B12:B61,5),Analysis!B12:B61,0))} -> Paul Baker | B21: 8309.74

Sheet Dashboard
