Workbook
Name Slicer_Customer_Name: #N/A
Name Slicer_City: #N/A

Sheet Dashboard

Sheet Top 5 customer by revenue
A3: Customer_Name | B3: Sum of Final_Amount
A4: Aanya | B4: 179195.98
A5: Aarav | B5: 179959.06
A6: Arjun | B6: 161050.91
A7: Diya | B7: 164368.97
A8: Isha | B8: 167272.26
A9: Kabir | B9: 192360.52
A10: Priya | B10: 147979.43
A11: Rohan | B11: 167011.61
A12: Sneha | B12: 201041.14
A13: Vivaan | B13: 197375.93
A14: Grand Total | B14: 1757615.8

Sheet City wise Customer
A3: City | B3: Count of Customer_Name
A4: Ahmedabad | B4: 94
A5: Bangalore | B5: 110
A6: Chennai | B6: 104
A7: Delhi | B7: 116
A8: Hyderabad | B8: 96
A9: Jaipur | B9: 99
A10: Kolkata | B10: 78
A11: Mumbai | B11: 100
A12: Pune | B12: 91
A13: Surat | B13: 112
A14: Grand Total | B14: 1000

Sheet Monthly Sales
A3: Month | B3: Sum of Final_Amount
A4: Jan | B4: 160097.26
A5: Feb | B5: 166469.65
A6: Mar | B6: 169968.72
A7: Apr | B7: 146677.87
A8: May | B8: 167995.36
A9: Jun | B9: 190166.67
A10: Jul | B10: 191515.82
A11: Aug | B11: 195646.87
A12: Sep | B12: 181924.61
A13: Oct | B13: 187152.98
A14: Grand Total | B14: 1757615.8

Sheet Payment By Sales
A3: Payment_Method | B3: Sum of Final_Amount
A4: Cash | B4: 304302.04
A5: Credit Card | B5: 324438.61
A6: Debit Card | B6: 269598.65
A7: Net Banking | B7: 292567.7
A8: UPI | B8: 263149.62
A9: Wallet | B9: 303559.19
A10: Grand Total | B10: 1757615.8

Sheet Item per Quentity
A3: Cuisine_Type | B3: Sum of Quantity
A4: American | B4: 484
A5: Chinese | B5: 429
A6: Indian | B6: 350
A7: Italian | B7: 435
A8: Japanese | B8: 374
A9: Mexican | B9: 489
A10: Thai | B10: 391
A11: Grand Total | B11: 2952

Sheet Resatorent By sales
A3: Restaurant_Name | B3: Sum of Final_Amount
A4: Biryani Bliss | B4: 146815.91
A5: Burger Hub | B5: 197283.45
A6: Curry Corner | B6: 197290.2
A7: Grill Master | B7: 190209.87
A8: Pasta Palace | B8: 144760.6
A9: Pizza Point | B9: 172570.01
A10: Spice Villa | B10: 163045.65
A11: Sushi Spot | B11: 174125.38
A12: Sweet Tooth | B12: 192487.95
A13: Tandoori Treats | B13: 179026.79
A14: Grand Total | B14: 1757615.8

Sheet Rawdata
A1: Order_ID | B1: Customer_Name | C1: Restaurant_Name | D1: City | E1: Cuisine_Type | F1: Item_Name | G1: Quantity | H1: Price_per_Item | I1: Total_Amount | J1: Discount_% | K1: Final_Amount | L1: Rating | M1: Payment_Method | N1: Delivery_Partner | O1: Delivery_Time_Minutes | P1: Order_Date | Q1: Month | R1: Year
A2: ORD1000 | B2: Kabir | C2: Burger Hub | D2: Mumbai | E2: Indian | F2: Indian Dish 28 | G2: 3 | H2: 1161.53 | I2: 3484.59 | J2: 15 | K2: 2961.9 | L2: 3 | M2: Debit Card | N2: Zomato Partner 2 | O2: 73 | P2: 45470 | Q2: =TEXT(P2,"mmm") -> Jun | R2: =YEAR(P2) -> 2024
A3: ORD1001 | B3: Priya | C3: Sushi Spot | D3: Bangalore | E3: American | F3: American Dish 28 | G3: 3 | H3: 1108.23 | I3: 3324.69 | J3: 0 | K3: 3324.69 | L3: 5 | M3: Cash | N3: Zomato Partner 1 | O3: 45 | P3: 45579 | Q3: =TEXT(P3,"mmm") -> Oct | R3: =YEAR(P3) -> 2024
A4: ORD1002 | B4: Sneha | C4: Grill Master | D4: Bangalore | E4: Italian | F4: Italian Dish 43 | G4: 3 | H4: 164.9 | I4: 494.7 | J4: 25 | K4: 371.02 | L4: 4 | M4: Debit Card | N4: Zomato Partner 4 | O4: 34 | P4: 45454 | Q4: =TEXT(P4,"mmm") -> Jun | R4: =YEAR(P4) -> 2024
A5: ORD1003 | B5: Rohan | C5: Pizza Point | D5: Jaipur | E5: American | F5: American Dish 1 | G5: 4 | H5: 1140.49 | I5: 4561.96 | J5: 0 | K5: 4561.96 | L5: 2 | M5: Wallet | N5: Zomato Partner 4 | O5: 32 | P5: 45588 | Q5: =TEXT(P5,"mmm") -> Oct | R5: =YEAR(P5) -> 2024
A6: ORD1004 | B6: Aanya | C6: Pasta Palace | D6: Pune | E6: American | F6: American Dish 35 | G6: 2 | H6: 780.99 | I6: 1561.98 | J6: 10 | K6: 1405.78 | L6: 2 | M6: UPI | N6: Zomato Partner 2 | O6: 21 | P6: 45389 | Q6: =TEXT(P6,"mmm") -> Apr | R6: =YEAR(P6) -> 2024
A7: ORD1005 | B7: Isha | C7: Spice Villa | D7: Chennai | E7: Italian | F7: Italian Dish 33 | G7: 1 | H7: 884.28 | I7: 884.28 | J7: 20 | K7: 707.42 | L7: 4 | M7: Cash | N7: Zomato Partner 4 | O7: 65 | P7: 45472 | Q7: =TEXT(P7,"mmm") -> Jun | R7: =YEAR(P7) -> 2024
A8: ORD1006 | B8: Rohan | C8: Sushi Spot | D8: Kolkata | E8: Indian | F8: Indian Dish 12 | G8: 4 | H8: 599.8 | I8: 2399.2 | J8: 15 | K8: 2039.32 | L8: 2 | M8: Net Banking | N8: Zomato Partner 2 | O8: 75 | P8: 45569 | Q8: =TEXT(P8,"mmm") -> Oct | R8: =YEAR(P8) -> 2024
A9: ORD1007 | B9: Kabir | C9: Curry Corner | D9: Chennai | E9: American | F9: American Dish 40 | G9: 1 | H9: 1195.13 | I9: 1195.13 | J9: 15 | K9: 1015.86 | L9: 1 | M9: Credit Card | N9: Zomato Partner 1 | O9: 33 | P9: 45502 | Q9: =TEXT(P9,"mmm") -> Jul | R9: =YEAR(P9) -> 2024
A10: ORD1008 | B10: Sneha | C10: Sushi Spot | D10: Delhi | E10: American | F10: American Dish 29 | G10: 5 | H10: 760.3 | I10: 3801.5 | J10: 5 | K10: 3611.42 | L10: 1 | M10: Wallet | N10: Zomato Partner 3 | O10: 47 | P10: 45507 | Q10: =TEXT(P10,"mmm") -> Aug | R10: =YEAR(P10) -> 2024
A11: ORD1009 | B11: Priya | C11: Sushi Spot | D11: Pune | E11: Indian | F11: Indian Dish 13 | G11: 4 | H11: 1148.08 | I11: 4592.32 | J11: 10 | K11: 4133.09 | L11: 3 | M11: Cash | N11: Zomato Partner 4 | O11: 20 | P11: 45494 | Q11: =TEXT(P11,"mmm") -> Jul | R11: =YEAR(P11) -> 2024
A12: ORD1010 | B12: Aanya | C12: Sushi Spot | D12: Chennai | E12: Italian | F12: Italian Dish 43 | G12: 3 | H12: 472.77 | I12: 1418.31 | J12: 0 | K12: 1418.31 | L12: 4 | M12: Wallet | N12: Zomato Partner 2 | O12: 73 | P12: 45294 | Q12: =TEXT(P12,"mmm") -> Jan | R12: =YEAR(P12) -> 2024
A13: ORD1011 | B13: Aarav | C13: Spice Villa | D13: Bangalore | E13: Thai | F13: Thai Dish 24 | G13: 5 | H13: 1011.04 | I13: 5055.2 | J13: 5 | K13: 4802.44 | L13: 5 | M13: UPI | N13: Zomato Partner 3 | O13: 75 | P13: 45379 | Q13: =TEXT(P13,"mmm") -> Mar | R13: =YEAR(P13) -> 2024
... A1001: ORD1999 | B1001: Kabir | C1001: Sweet Tooth | D1001: Jaipur | E1001: Chinese | F1001: Chinese Dish 49 | G1001: 5 | H1001: 1161 | I1001: 5805 | J1001: 25 | K1001: 4353.75 | L1001: 3 | M1001: Debit Card | N1001: Zomato Partner 1 | O1001: 53 | P1001: 45388 | Q1001: =TEXT(P1001,"mmm") -> Apr | R1001: =YEAR(P1001) -> 2024

Sheet analysis
A1: Customer wise sales | E1: Metric | J1: Monthly sales
A2: Customer Name | B2: Total Sales | C2: Avarege Discount % | F2: Value | J2: Month | K2: Total sales | L2: Last Month Sales | M2: Growth Rate %
A3: {=_xlfn.UNIQUE(Rawdata!B2:B1001)} -> Kabir | B3: =SUMIFS(Rawdata!K2:K1001,Rawdata!B2:B1001,A3) -> 192360.52 | C3: =AVERAGEIFS(Rawdata!J2:J1001,Rawdata!B2:B1001,A3) -> 10.959596 | E3: Total Revenue | F3: =SUM(B3:B12) -> 1757615.8 | J3: {=_xlfn.UNIQUE(Rawdata!Q2:Q1001)} -> Jun | K3: =SUMIFS(Rawdata!K2:K1001,Rawdata!Q2:Q1001,J3) -> 190166.67 | L3: 0 | M3: =IFERROR((K3-L3)/L3,"")
A4: Priya | B4: =SUMIFS(Rawdata!K3:K1002,Rawdata!B3:B1002,A4) -> 147979.43 | C4: =AVERAGEIFS(Rawdata!J3:J1002,Rawdata!B3:B1002,A4) -> 11.280488 | E4: Total Transaction | F4: =COUNTA(Rawdata!A2:A1001) -> 1000 | J4: Oct | K4: =SUMIFS(Rawdata!K3:K1002,Rawdata!Q3:Q1002,J4) -> 187152.98 | L4: =K3 -> 190166.67 | M4: =IFERROR((K4-L4)/L4,"") -> -0.015847625
A5: Sneha | B5: =SUMIFS(Rawdata!K4:K1003,Rawdata!B4:B1003,A5) -> 201041.14 | C5: =AVERAGEIFS(Rawdata!J4:J1003,Rawdata!B4:B1003,A5) -> 12.209302 | E5: Avarage Discount % | F5: =AVERAGE(C3:C12) -> 12.012796 | J5: Apr | K5: =SUMIFS(Rawdata!K4:K1003,Rawdata!Q4:Q1003,J5) -> 146677.87 | L5: =K4 -> 187152.98 | M5: =IFERROR((K5-L5)/L5,"") -> -0.21626752
A6: Rohan | B6: =SUMIFS(Rawdata!K5:K1004,Rawdata!B5:B1004,A6) -> 167011.61 | C6: =AVERAGEIFS(Rawdata!J5:J1004,Rawdata!B5:B1004,A6) -> 12.580645 | E6: Total Quentity | F6: =SUM(J16:J25) -> 2952 | J6: Jul | K6: =SUMIFS(Rawdata!K5:K1004,Rawdata!Q5:Q1004,J6) -> 191515.82 | L6: =K5 -> 146677.87 | M6: =IFERROR((K6-L6)/L6,"") -> 0.30568994
A7: Aanya | B7: =SUMIFS(Rawdata!K6:K1005,Rawdata!B6:B1005,A7) -> 179195.98 | C7: =AVERAGEIFS(Rawdata!J6:J1005,Rawdata!B6:B1005,A7) -> 11.971154 | E7: Top Customer | F7: {=INDEX(_xlfn.ANCHORARRAY(A3),MATCH(MAX(B3:B12),B3:B12,0))} -> Sneha | G7: =MAX(B3:B12) -> 201041.14 | J7: Aug | K7: =SUMIFS(Rawdata!K6:K1005,Rawdata!Q6:Q1005,J7) -> 195646.87 | L7: =K6 -> 191515.82 | M7: =IFERROR((K7-L7)/L7,"") -> 0.021570281
A8: Isha | B8: =SUMIFS(Rawdata!K7:K1006,Rawdata!B7:B1006,A8) -> 167272.26 | C8: =AVERAGEIFS(Rawdata!J7:J1006,Rawdata!B7:B1006,A8) -> 13.232323 | E8: Top City | F8: {=INDEX(_xlfn.ANCHORARRAY(A17),MATCH(MAX(B17:B26),B17:B26,0))} -> Chennai | G8: =MAX(B17:B26) -> 198451.56 | J8: Jan | K8: =SUMIFS(Rawdata!K7:K1006,Rawdata!Q7:Q1006,J8) -> 160097.26 | L8: =K7 -> 195646.87 | M8: =IFERROR((K8-L8)/L8,"") -> -0.18170293
A9: Aarav | B9: =SUMIFS(Rawdata!K8:K1007,Rawdata!B8:B1007,A9) -> 179959.06 | C9: =AVERAGEIFS(Rawdata!J8:J1007,Rawdata!B8:B1007,A9) -> 11.789474 | E9: Top Restaurant Name | F9: {=INDEX(_xlfn.ANCHORARRAY(H16),MATCH(MAX(I16:I25),I16:I25,0))} -> Curry Corner | G9: =MAX(I16:I25) -> 197290.2 | J9: Mar | K9: =SUMIFS(Rawdata!K8:K1007,Rawdata!Q8:Q1007,J9) -> 169968.72 | L9: =K8 -> 160097.26 | M9: =IFERROR((K9-L9)/L9,"") -> 0.061659144
A10: Arjun | B10: =SUMIFS(Rawdata!K9:K1008,Rawdata!B9:B1008,A10) -> 161050.91 | C10: =AVERAGEIFS(Rawdata!J9:J1008,Rawdata!B9:B1008,A10) -> 11.902174 | E10: Top Month Sales | F10: {=INDEX(_xlfn.ANCHORARRAY(J3),MATCH(MAX(K3:K12),K3:K12,0))} -> Aug | G10: =MAX(K3:K12) -> 195646.87 | J10: Sep | K10: =SUMIFS(Rawdata!K9:K1008,Rawdata!Q9:Q1008,J10) -> 181924.61 | L10: =K9 -> 169968.72 | M10: =IFERROR((K10-L10)/L10,"") -> 0.070341708
A11: Diya | B11: =SUMIFS(Rawdata!K10:K1009,Rawdata!B10:B1009,A11) -> 164368.97 | C11: =AVERAGEIFS(Rawdata!J10:J1009,Rawdata!B10:B1009,A11) -> 12.1 | E11: Avarage Deliverytime( In Minute) | F11: =AVERAGE(Rawdata!O2:O1001) -> 54.401 | J11: Feb | K11: =SUMIFS(Rawdata!K10:K1009,Rawdata!Q10:Q1009,J11) -> 166469.65 | L11: =K10 -> 181924.61 | M11: =IFERROR((K11-L11)/L11,"") -> -0.084952553
A12: Vivaan | B12: =SUMIFS(Rawdata!K11:K1010,Rawdata!B11:B1010,A12) -> 197375.93 | C12: =AVERAGEIFS(Rawdata!J11:J1010,Rawdata!B11:B1010,A12) -> 12.102804 | E12: Avarge Price per Item | F12: =AVERAGE(Rawdata!H2:H1001) -> 677.69065 | J12: May | K12: =SUMIFS(Rawdata!K11:K1010,Rawdata!Q11:Q1010,J12) -> 167995.36 | L12: =K11 -> 166469.65 | M12: =IFERROR((K12-L12)/L12,"") -> 0.0091650941
A13: Total | B13: =SUM(B3:B12) -> 1757615.8
A15: City wise sales | E15: cuisine Type | F15: Total Quentity | H15: Restaurant_Name | I15: Total Sales | J15: Total Quentity | K15: Avarage Rating
A16: City | B16: Total Sales | E16: {=_xlfn.UNIQUE(Rawdata!E2:E1001)} -> Indian | F16: =SUMIFS(Rawdata!K2:K1001,Rawdata!E2:E1001,E16) -> 209059.63 | H16: {=_xlfn.UNIQUE(Rawdata!C2:C1001)} -> Burger Hub | I16: =SUMIFS(Rawdata!K2:K1001,Rawdata!C2:C1001,H16) -> 197283.45 | J16: =SUMIFS(Rawdata!G2:G1001,Rawdata!C2:C1001,H16) -> 333 | K16: =AVERAGEIFS(Rawdata!L2:L1001,Rawdata!C2:C1001,H16) -> 2.7964602
A17: {=_xlfn.UNIQUE(Rawdata!D2:D1001)} -> Mumbai | B17: =SUMIFS(Rawdata!K2:K1001,Rawdata!D2:D1001,A17) -> 179927.72 | E17: American | F17: =SUMIFS(Rawdata!K3:K1002,Rawdata!E3:E1002,E17) -> 284680.1 | H17: Sushi Spot | I17: =SUMIFS(Rawdata!K3:K1002,Rawdata!C3:C1002,H17) -> 174125.38 | J17: =SUMIFS(Rawdata!G3:G1002,Rawdata!C3:C1002,H17) -> 306 | K17: =AVERAGEIFS(Rawdata!L3:L1002,Rawdata!C3:C1002,H17) -> 2.8823529
A18: Bangalore | B18: =SUMIFS(Rawdata!K3:K1002,Rawdata!D3:D1002,A18) -> 195116.34 | E18: Italian | F18: =SUMIFS(Rawdata!K4:K1003,Rawdata!E4:E1003,E18) -> 254945.45 | H18: Grill Master | I18: =SUMIFS(Rawdata!K4:K1003,Rawdata!C4:C1003,H18) -> 190209.87 | J18: =SUMIFS(Rawdata!G4:G1003,Rawdata!C4:C1003,H18) -> 307 | K18: =AVERAGEIFS(Rawdata!L4:L1003,Rawdata!C4:C1003,H18) -> 3.038835
A19: Jaipur | B19: =SUMIFS(Rawdata!K4:K1003,Rawdata!D4:D1003,A19) -> 196597.16 | E19: Thai | F19: =SUMIFS(Rawdata!K5:K1004,Rawdata!E5:E1004,E19) -> 229907.95 | H19: Pizza Point | I19: =SUMIFS(Rawdata!K5:K1004,Rawdata!C5:C1004,H19) -> 172570.01 | J19: =SUMIFS(Rawdata!G5:G1004,Rawdata!C5:C1004,H19) -> 284 | K19: =AVERAGEIFS(Rawdata!L5:L1004,Rawdata!C5:C1004,H19) -> 3.127451
A20: Pune | B20: =SUMIFS(Rawdata!K5:K1004,Rawdata!D5:D1004,A20) -> 155222.37 | E20: Japanese | F20: =SUMIFS(Rawdata!K6:K1005,Rawdata!E6:E1005,E20) -> 223555.9 | H20: Pasta Palace | I20: =SUMIFS(Rawdata!K6:K1005,Rawdata!C6:C1005,H20) -> 144760.6 | J20: =SUMIFS(Rawdata!G6:G1005,Rawdata!C6:C1005,H20) -> 238 | K20: =AVERAGEIFS(Rawdata!L6:L1005,Rawdata!C6:C1005,H20) -> 2.8295455
A21: Chennai | B21: =SUMIFS(Rawdata!K6:K1005,Rawdata!D6:D1005,A21) -> 198451.56 | E21: Mexican | F21: =SUMIFS(Rawdata!K7:K1006,Rawdata!E7:E1006,E21) -> 302477.07 | H21: Spice Villa | I21: =SUMIFS(Rawdata!K7:K1006,Rawdata!C7:C1006,H21) -> 163045.65 | J21: =SUMIFS(Rawdata!G7:G1006,Rawdata!C7:C1006,H21) -> 255 | K21: =AVERAGEIFS(Rawdata!L7:L1006,Rawdata!C7:C1006,H21) -> 2.6097561
A22: Kolkata | B22: =SUMIFS(Rawdata!K7:K1006,Rawdata!D7:D1006,A22) -> 121475.08 | E22: Chinese | F22: =SUMIFS(Rawdata!K8:K1007,Rawdata!E8:E1007,E22) -> 252989.71 | H22: Curry Corner | I22: =SUMIFS(Rawdata!K8:K1007,Rawdata!C8:C1007,H22) -> 197290.2 | J22: =SUMIFS(Rawdata!G8:G1007,Rawdata!C8:C1007,H22) -> 332 | K22: =AVERAGEIFS(Rawdata!L8:L1007,Rawdata!C8:C1007,H22) -> 3.1637931
A23: Delhi | B23: =SUMIFS(Rawdata!K8:K1007,Rawdata!D8:D1007,A23) -> 196788.53 | H23: Tandoori Treats | I23: =SUMIFS(Rawdata!K9:K1008,Rawdata!C9:C1008,H23) -> 179026.79 | J23: =SUMIFS(Rawdata!G9:G1008,Rawdata!C9:C1008,H23) -> 314 | K23: =AVERAGEIFS(Rawdata!L9:L1008,Rawdata!C9:C1008,H23) -> 2.7216495
A24: Hyderabad | B24: =SUMIFS(Rawdata!K9:K1008,Rawdata!D9:D1008,A24) -> 167547.83 | H24: Biryani Bliss | I24: =SUMIFS(Rawdata!K10:K1009,Rawdata!C10:C1009,H24) -> 146815.91 | J24: =SUMIFS(Rawdata!G10:G1009,Rawdata!C10:C1009,H24) -> 251 | K24: =AVERAGEIFS(Rawdata!L10:L1009,Rawdata!C10:C1009,H24) -> 3.1235955
A25: Ahmedabad | B25: =SUMIFS(Rawdata!K10:K1009,Rawdata!D10:D1009,A25) -> 171473.81 | H25: Sweet Tooth | I25: =SUMIFS(Rawdata!K11:K1010,Rawdata!C11:C1010,H25) -> 192487.95 | J25: =SUMIFS(Rawdata!G11:G1010,Rawdata!C11:C1010,H25) -> 332 | K25: =AVERAGEIFS(Rawdata!L11:L1010,Rawdata!C11:C1010,H25) -> 2.9351852
A26: Surat | B26: =SUMIFS(Rawdata!K11:K1010,Rawdata!D11:D1010,A26) -> 175015.41

Sheet Summary
A3: 🍽️ ZOMATO SALES DASHBOARD SUMMARY
A5: 📊 Overall Metrics
A7: Total Revenue: ₹1,757,615.81
A9: Total Transactions: 1,000
A11: Total Quantity Sold: 2,952
A13: Average Discount: 12.01%
A15: Average Price per Item: ₹677.69
A17: Average Delivery Time: 54 minutes
A19: 👤 Top Performers
A21: Top Customer: Sneha — ₹201,041.14
A23: Top City: Chennai — ₹198,451.56
A25: Top Restaurant: Curry Corner — ₹197,290.20
... A31: 📅 Monthly Sales Trend
A33: Month | B33: Total Sales | C33: Growth Rate
A34: June | B34: ₹190,166.67 | C34: —
A35: July | B35: ₹191,515.82 | C35: ⬆ 31%
A36: August | B36: ₹195,646.87 | C36: ⬆ 2%
A37: September | B37: ₹181,924.61 | C37: ⬆ 7%
A38: October | B38: ₹187,152.98 | C38: ⬇ 2%
A39: Others | B39: ₹160k–₹170k range | C39: —
A41: 🏙️ City Wise Sales
A43: City | B43: Total Sales
A44: Chennai | B44: ₹198,451.56
A45: Delhi | B45: ₹196,788.53
A46: Jaipur | B46: ₹196,597.16
A47: Bangalore | B47: ₹195,116.34
A48: Mumbai | B48: ₹179,927.72
A50: Top City: Chennai
A51: Lowest Sales: Kolkata (₹121,475.08)
A53: 🏢 Restaurant Insights
A55: Restaurant | B55: Sales | C55: Rating
A56: Curry Corner | B56: ₹197,290.20 | C56: ⭐3
A57: Burger Hub | B57: ₹197,283.45 | C57: ⭐3
A58: Sweet Tooth | B58: ₹192,487.95 | C58: ⭐3
A59: Grill Master | B59: ₹190,209.87 | C59: ⭐3
A61: ✅ Top Restaurant: Curry Corner
A62: ⭐ Average Rating: 3
